drhash/WeightedMinHash.py
drhash/__init__.py
drhash-0.1.1.dist-info/LICENSE
drhash-0.1.1.dist-info/METADATA
drhash-0.1.1.dist-info/WHEEL
drhash-0.1.1.dist-info/top_level.txt
drhash-0.1.1.dist-info/RECORD
