Metadata-Version: 2.1
Name: drhash
Version: 0.1.1
Summary: drhash is a software package for data representation via similarity-preserved hashing algorithms
Home-page: https://github.com/drhash-cn
Author: Wei Wu
Author-email: william.third.wu@gmail.com
License: UNKNOWN
Platform: UNKNOWN
Classifier: Programming Language :: Python :: 3
Classifier: License :: OSI Approved :: MIT License
Classifier: Operating System :: OS Independent
Requires-Dist: numpy (>=1.15.0)
Requires-Dist: scipy (>=1.1.0)
